zyt_validation_utils/__init__.py
zyt_validation_utils/config.py
zyt_validation_utils/data_check.py
zyt_validation_utils/dir_check.py
zyt_validation_utils/file_check.py
zyt_validation_utils/text_check.py
zyt_validation_utils-0.2.4.dist-info/METADATA
zyt_validation_utils-0.2.4.dist-info/WHEEL
zyt_validation_utils-0.2.4.dist-info/top_level.txt
zyt_validation_utils-0.2.4.dist-info/RECORD
