Metadata-Version: 2.1
Name: zyt-validation-utils
Version: 0.2.4
Summary: A utility package for various validation checks
Home-page: https://github.com/yourusername
Author: ZhangYuetao
Author-email: zhang894171707@gmail.com
License: UNKNOWN
Platform: UNKNOWN
Classifier: Programming Language :: Python :: 3
Classifier: License :: OSI Approved :: MIT License
Classifier: Operating System :: OS Independent
Requires-Python: >=3.6
Requires-Dist: Pillow
Requires-Dist: filetype
